streamsage_python_logger/__init__.py
streamsage_python_logger/streamsage_logger.py
streamsage_python_logger/logger_configuration/__init__.py
streamsage_python_logger/logger_configuration/formatters.py
streamsage_python_logger/logger_configuration/handlers.py
streamsage_python_logger/settings/__init__.py
streamsage_python_logger/settings/settings.py
streamsage_python_logger-0.0.20.dist-info/LICENSE
streamsage_python_logger-0.0.20.dist-info/METADATA
streamsage_python_logger-0.0.20.dist-info/WHEEL
streamsage_python_logger-0.0.20.dist-info/top_level.txt
streamsage_python_logger-0.0.20.dist-info/RECORD
