Metadata-Version: 2.1
Name: streamsage-python-logger
Version: 0.0.20
Summary: StreamSage Python Logger
Author: streamsage
Author-email: streamsage <dev@streamsage.io>
License: Copyright (c) 2018 The Python Packaging Authority        
Classifier: Programming Language :: Python :: 3
Classifier: License :: OSI Approved :: MIT License
Classifier: Operating System :: OS Independent
Requires-Python: >=3.8
License-File: LICENSE
Requires-Dist: fluent-logger (==0.10.0)
Requires-Dist: pydantic (~=1.8.0)
Requires-Dist: python-dotenv (==0.19.1)
